arcane_mage/__init__.py
arcane_mage/__main__.py
arcane_mage/arcane_mage.py
arcane_mage/arcane_mage.tcss
arcane_mage/helpers.py
arcane_mage/log.py
arcane_mage/messages.py
arcane_mage/models.py
arcane_mage/password.py
arcane_mage/proxmox.py
arcane_mage/py.typed
arcane_mage/images/__init__.py
arcane_mage/images/arcane_config.raw.gz
arcane_mage/images/arcane_efi.raw.gz
arcane_mage/screens/__init__.py
arcane_mage/screens/confirm_screen.py
arcane_mage/screens/hypervisor.py
arcane_mage/screens/provision_node.py
arcane_mage/screens/provisioning_info.py
arcane_mage/screens/welcome.py
arcane_mage/screens/welcome_proxmox.py
arcane_mage/widgets/__init__.py
arcane_mage/widgets/spinner.py
arcane_mage-0.3.4.dist-info/METADATA
arcane_mage-0.3.4.dist-info/WHEEL
arcane_mage-0.3.4.dist-info/entry_points.txt
arcane_mage-0.3.4.dist-info/licenses/LICENSE
arcane_mage-0.3.4.dist-info/RECORD
