Metadata-Version: 2.4
Name: arcane-mage
Version: 0.3.4
Summary: Automation helper for Fluxnodes
Author-email: David White <david@runonflux.io>
License-File: LICENSE
Requires-Python: >=3.12.0
Requires-Dist: aiofiles>=24.1.0
Requires-Dist: aiohttp>=3.11.18
Requires-Dist: click>=8.2.1
Requires-Dist: email-validator>=2.2.0
Requires-Dist: httpx>=0.28.1
Requires-Dist: keyring<25.7,>=25.6.0
Requires-Dist: pydantic>=2.11.4
Requires-Dist: pyescrypt>=0.1.0
Requires-Dist: pyfatfs>=1.1.0
Requires-Dist: pyroute2>=0.9.2
Requires-Dist: python-iptables>=1.2.0
Requires-Dist: pyyaml>=6.0.2
Requires-Dist: sshpubkeys>=3.3.1
Requires-Dist: textual>=3.2.0
